[
  {
    "id": "plastilina",
    "nombre": "La Vida en Plastilina",
    "estilos": {
      "fondo_tipo": "imagen",
      "fondo_color1": "#1a1a2e",
      "fondo_color2": "#546492",
      "fondo_direccion": "vertical",
      "texto_tipo": "solido",
      "color_texto": "#ffffff",
      "texto_color2": "#000000",
      "texto_direccion": "vertical",
      "fuente_principal": "Raleway",
      "fuente_datos": "Fira Code",
      "fuentes_custom": [],
      "color_acento1": "#ffffff",
      "color_acento2": "#ff0000",
      "tamano_titulo": 55,
      "tamano_texto": 35,
      "tamano_dato": 123,
      "padding_porcentaje": 10,
      "icono_nombre": "",
      "icono_color": "#5b4cf5",
      "icono_posicion": "arriba",
      "icono_tamano": 39,
      "icono_opacidad": 0.25,
      "fondo_imagen": "brand/backgrounds/plastilina.jpeg",
      "fondo_video": null,
      "overlay_color": "#000000",
      "overlay_opacidad": 0.4,
      "glassmorphism": true,
      "glass_blur": 20,
      "glass_saturacion": 120,
      "glass_borde": true,
      "anim_entrada": "fadeUp",
      "anim_salida": "none",
      "anim_icono": "popIn"
    }
  },
  {
    "id": "perfil_1779398432737",
    "nombre": "Sofos",
    "estilos": {
      "fondo_tipo": "video",
      "fondo_color1": "#c2b291",
      "fondo_color2": "#16213e",
      "fondo_direccion": "diagonal",
      "texto_tipo": "solido",
      "color_texto": "#a22f2f",
      "texto_color2": "#0da892",
      "texto_direccion": "horizontal",
      "fuente_principal": "Concert one",
      "fuente_datos": "Oswald",
      "fuentes_custom": [
        "Concert one",
        "Oswald"
      ],
      "color_acento1": "#ffffff",
      "color_acento2": "#ffffff",
      "tamano_titulo": 48,
      "tamano_texto": 48,
      "tamano_dato": 107,
      "padding_porcentaje": 10,
      "icono_nombre": "",
      "icono_color": "#5b4cf5",
      "icono_posicion": "arriba",
      "icono_tamano": 48,
      "icono_opacidad": 1,
      "fondo_imagen": null,
      "fondo_video": "brand/backgrounds/perfil_1779398432737.mp4",
      "overlay_color": "#1a1a19",
      "overlay_opacidad": 0.7,
      "glassmorphism": false,
      "glass_blur": 20,
      "glass_saturacion": 120,
      "glass_borde": true,
      "anim_entrada": "fadeUp",
      "anim_salida": "fadeOut",
      "anim_icono": "popIn"
    }
  }
]